SimpleWindow/SimpleWindow.py
SimpleWindow/__init__.py
simplewindow-1.1.dist-info/licenses/LICENSE
simplewindow-1.1.dist-info/METADATA
simplewindow-1.1.dist-info/WHEEL
simplewindow-1.1.dist-info/top_level.txt
simplewindow-1.1.dist-info/RECORD
