Metadata-Version: 2.4
Name: SimpleWindow
Version: 1.1
Summary: A package to easily create and manage windows in Python
Author: OleFranz
License:                     GNU GENERAL PUBLIC LICENSE
Requires-Python: >=3.9
License-File: LICENSE
Requires-Dist: glfw
Requires-Dist: numpy
Requires-Dist: opencv-python
Requires-Dist: PyOpenGL
Requires-Dist: pywin32
Dynamic: license-file
Dynamic: requires-python
